MANIFEST.in
README.rst
setup.cfg
setup.py
ckanext/__init__.py
ckanext/restricted/__init__.py
ckanext/restricted/controller.py
ckanext/restricted/helpers.py
ckanext/restricted/logic.py
ckanext/restricted/plugin.py
ckanext/restricted/public/restricted_theme.css
ckanext/restricted/templates/base.html
ckanext/restricted/templates/package/snippets/resource_item.html
ckanext/restricted/templates/restricted/restricted_request_access_base.html
ckanext/restricted/templates/restricted/restricted_request_access_form.html
ckanext/restricted/templates/restricted/restricted_request_access_result.html
ckanext/restricted/tests/__init__.py
ckanext/restricted/tests/test_plugin.py
ckanext_restricted.egg-info/PKG-INFO
ckanext_restricted.egg-info/SOURCES.txt
ckanext_restricted.egg-info/dependency_links.txt
ckanext_restricted.egg-info/entry_points.txt
ckanext_restricted.egg-info/pbr.json
ckanext_restricted.egg-info/top_level.txt