Metadata-Version: 1.1
Name: ckanext-restricted
Version: 0.0.2
Summary: Data restricting access extension for CKAN
Home-page: https://github.com/espona/ckanext-restricted
Author: Lucia Espona Pernas
Author-email: lucia.espona@gmail.com
License: AGPL
Keywords: CKAN restrict access resource
Platform: UNKNOWN
Classifier: Development Status :: 4 - Beta
Classifier: License :: OSI Approved :: GNU Affero General Public License v3 or later (AGPLv3+)
Classifier: Programming Language :: Python :: 2.6
Classifier: Programming Language :: Python :: 2.7
